blis-1.3.1.dist-info/RECORD
blis-1.3.1.dist-info/WHEEL
blis-1.3.1.dist-info/top_level.txt
blis-1.3.1.dist-info/METADATA
blis-1.3.1.dist-info/licenses/LICENSE
blis/cy.cpython-311-darwin.so
blis/benchmark.py
blis/cy.pyx
blis/__init__.pxd
blis/py.pyx
blis/__init__.py
blis/about.py
blis/py.cpython-311-darwin.so
blis/cy.pxd
blis/tests/__init__.py
blis/tests/test_dotv.py
blis/tests/test_gemm.py
blis/tests/common.py
